[{
  "url": "https://api.github.com/repos/iluwatar/java-design-patterns/pulls/663",
  "id": 150696317,
  "html_url": "https://github.com/iluwatar/java-design-patterns/pull/663",
  "diff_url": "https://github.com/iluwatar/java-design-patterns/pull/663.diff",
  "patch_url": "https://github.com/iluwatar/java-design-patterns/pull/663.patch",
  "issue_url": "https://api.github.com/repos/iluwatar/java-design-patterns/issues/663",
  "number": 663,
  "state": "open",
  "locked": false,
  "title": "#114 Added eip-aggregator",
  "user": {
    "login": "codinghog",
    "id": 868566,
    "avatar_url": "https://avatars2.githubusercontent.com/u/868566?v=4",
    "gravatar_id": "",
    "url": "https://api.github.com/users/codinghog",
    "html_url": "https://github.com/codinghog",
    "followers_url": "https://api.github.com/users/codinghog/followers",
    "following_url": "https://api.github.com/users/codinghog/following{/other_user}",
    "gists_url": "https://api.github.com/users/codinghog/gists{/gist_id}",
    "starred_url": "https://api.github.com/users/codinghog/starred{/owner}{/repo}",
    "subscriptions_url": "https://api.github.com/users/codinghog/subscriptions",
    "organizations_url": "https://api.github.com/users/codinghog/orgs",
    "repos_url": "https://api.github.com/users/codinghog/repos",
    "events_url": "https://api.github.com/users/codinghog/events{/privacy}",
    "received_events_url": "https://api.github.com/users/codinghog/received_events",
    "type": "User",
    "site_admin": false
  },
  "body": "New pattern - eip-aggregator. Added description, code, tests.",
  "created_at": "2017-11-04T21:45:39Z",
  "updated_at": "2017-11-04T21:45:39Z",
  "closed_at": null,
  "merged_at": null,
  "merge_commit_sha": "3bc3258e8a7cec0c360d46fae7a4ff33e4a574a2",
  "assignee": null,
  "assignees": [

  ],
  "requested_reviewers": [

  ],
  "milestone": null,
  "commits_url": "https://api.github.com/repos/iluwatar/java-design-patterns/pulls/663/commits",
  "review_comments_url": "https://api.github.com/repos/iluwatar/java-design-patterns/pulls/663/comments",
  "review_comment_url": "https://api.github.com/repos/iluwatar/java-design-patterns/pulls/comments{/number}",
  "comments_url": "https://api.github.com/repos/iluwatar/java-design-patterns/issues/663/comments",
  "statuses_url": "https://api.github.com/repos/iluwatar/java-design-patterns/statuses/6e0bf59e5a7e2a768f0ddc923178e8153ba3c0ce",
  "head": {
    "label": "codinghog:master",
    "ref": "master",
    "sha": "6e0bf59e5a7e2a768f0ddc923178e8153ba3c0ce",
    "user": {
      "login": "codinghog",
      "id": 868566,
      "avatar_url": "https://avatars2.githubusercontent.com/u/868566?v=4",
      "gravatar_id": "",
      "url": "https://api.github.com/users/codinghog",
      "html_url": "https://github.com/codinghog",
      "followers_url": "https://api.github.com/users/codinghog/followers",
      "following_url": "https://api.github.com/users/codinghog/following{/other_user}",
      "gists_url": "https://api.github.com/users/codinghog/gists{/gist_id}",
      "starred_url": "https://api.github.com/users/codinghog/starred{/owner}{/repo}",
      "subscriptions_url": "https://api.github.com/users/codinghog/subscriptions",
      "organizations_url": "https://api.github.com/users/codinghog/orgs",
      "repos_url": "https://api.github.com/users/codinghog/repos",
      "events_url": "https://api.github.com/users/codinghog/events{/privacy}",
      "received_events_url": "https://api.github.com/users/codinghog/received_events",
      "type": "User",
      "site_admin": false
    },
    "repo": {
      "id": 105504562,
      "name": "java-design-patterns",
      "full_name": "codinghog/java-design-patterns",
      "owner": {
        "login": "codinghog",
        "id": 868566,
        "avatar_url": "https://avatars2.githubusercontent.com/u/868566?v=4",
        "gravatar_id": "",
        "url": "https://api.github.com/users/codinghog",
        "html_url": "https://github.com/codinghog",
        "followers_url": "https://api.github.com/users/codinghog/followers",
        "following_url": "https://api.github.com/users/codinghog/following{/other_user}",
        "gists_url": "https://api.github.com/users/codinghog/gists{/gist_id}",
        "starred_url": "https://api.github.com/users/codinghog/starred{/owner}{/repo}",
        "subscriptions_url": "https://api.github.com/users/codinghog/subscriptions",
        "organizations_url": "https://api.github.com/users/codinghog/orgs",
        "repos_url": "https://api.github.com/users/codinghog/repos",
        "events_url": "https://api.github.com/users/codinghog/events{/privacy}",
        "received_events_url": "https://api.github.com/users/codinghog/received_events",
        "type": "User",
        "site_admin": false
      },
      "private": false,
      "html_url": "https://github.com/codinghog/java-design-patterns",
      "description": "Design patterns implemented in Java",
      "fork": true,
      "url": "https://api.github.com/repos/codinghog/java-design-patterns",
      "forks_url": "https://api.github.com/repos/codinghog/java-design-patterns/forks",
      "keys_url": "https://api.github.com/repos/codinghog/java-design-patterns/keys{/key_id}",
      "collaborators_url": "https://api.github.com/repos/codinghog/java-design-patterns/collaborators{/collaborator}",
      "teams_url": "https://api.github.com/repos/codinghog/java-design-patterns/teams",
      "hooks_url": "https://api.github.com/repos/codinghog/java-design-patterns/hooks",
      "issue_events_url": "https://api.github.com/repos/codinghog/java-design-patterns/issues/events{/number}",
      "events_url": "https://api.github.com/repos/codinghog/java-design-patterns/events",
      "assignees_url": "https://api.github.com/repos/codinghog/java-design-patterns/assignees{/user}",
      "branches_url": "https://api.github.com/repos/codinghog/java-design-patterns/branches{/branch}",
      "tags_url": "https://api.github.com/repos/codinghog/java-design-patterns/tags",
      "blobs_url": "https://api.github.com/repos/codinghog/java-design-patterns/git/blobs{/sha}",
      "git_tags_url": "https://api.github.com/repos/codinghog/java-design-patterns/git/tags{/sha}",
      "git_refs_url": "https://api.github.com/repos/codinghog/java-design-patterns/git/refs{/sha}",
      "trees_url": "https://api.github.com/repos/codinghog/java-design-patterns/git/trees{/sha}",
      "statuses_url": "https://api.github.com/repos/codinghog/java-design-patterns/statuses/{sha}",
      "languages_url": "https://api.github.com/repos/codinghog/java-design-patterns/languages",
      "stargazers_url": "https://api.github.com/repos/codinghog/java-design-patterns/stargazers",
      "contributors_url": "https://api.github.com/repos/codinghog/java-design-patterns/contributors",
      "subscribers_url": "https://api.github.com/repos/codinghog/java-design-patterns/subscribers",
      "subscription_url": "https://api.github.com/repos/codinghog/java-design-patterns/subscription",
      "commits_url": "https://api.github.com/repos/codinghog/java-design-patterns/commits{/sha}",
      "git_commits_url": "https://api.github.com/repos/codinghog/java-design-patterns/git/commits{/sha}",
      "comments_url": "https://api.github.com/repos/codinghog/java-design-patterns/comments{/number}",
      "issue_comment_url": "https://api.github.com/repos/codinghog/java-design-patterns/issues/comments{/number}",
      "contents_url": "https://api.github.com/repos/codinghog/java-design-patterns/contents/{+path}",
      "compare_url": "https://api.github.com/repos/codinghog/java-design-patterns/compare/{base}...{head}",
      "merges_url": "https://api.github.com/repos/codinghog/java-design-patterns/merges",
      "archive_url": "https://api.github.com/repos/codinghog/java-design-patterns/{archive_format}{/ref}",
      "downloads_url": "https://api.github.com/repos/codinghog/java-design-patterns/downloads",
      "issues_url": "https://api.github.com/repos/codinghog/java-design-patterns/issues{/number}",
      "pulls_url": "https://api.github.com/repos/codinghog/java-design-patterns/pulls{/number}",
      "milestones_url": "https://api.github.com/repos/codinghog/java-design-patterns/milestones{/number}",
      "notifications_url": "https://api.github.com/repos/codinghog/java-design-patterns/notifications{?since,all,participating}",
      "labels_url": "https://api.github.com/repos/codinghog/java-design-patterns/labels{/name}",
      "releases_url": "https://api.github.com/repos/codinghog/java-design-patterns/releases{/id}",
      "deployments_url": "https://api.github.com/repos/codinghog/java-design-patterns/deployments",
      "created_at": "2017-10-02T06:33:38Z",
      "updated_at": "2017-10-02T06:33:43Z",
      "pushed_at": "2017-11-04T21:39:10Z",
      "git_url": "git://github.com/codinghog/java-design-patterns.git",
      "ssh_url": "git@github.com:codinghog/java-design-patterns.git",
      "clone_url": "https://github.com/codinghog/java-design-patterns.git",
      "svn_url": "https://github.com/codinghog/java-design-patterns",
      "homepage": "http://java-design-patterns.com",
      "size": 16288,
      "stargazers_count": 0,
      "watchers_count": 0,
      "language": "Java",
      "has_issues": false,
      "has_projects": true,
      "has_downloads": true,
      "has_wiki": true,
      "has_pages": false,
      "forks_count": 0,
      "mirror_url": null,
      "archived": false,
      "open_issues_count": 0,
      "forks": 0,
      "open_issues": 0,
      "watchers": 0,
      "default_branch": "master"
    }
  },
  "base": {
    "label": "iluwatar:master",
    "ref": "master",
    "sha": "5ed46c2c6481c322673c6eacab918302ca1d5f13",
    "user": {
      "login": "iluwatar",
      "id": 582346,
      "avatar_url": "https://avatars1.githubusercontent.com/u/582346?v=4",
      "gravatar_id": "",
      "url": "https://api.github.com/users/iluwatar",
      "html_url": "https://github.com/iluwatar",
      "followers_url": "https://api.github.com/users/iluwatar/followers",
      "following_url": "https://api.github.com/users/iluwatar/following{/other_user}",
      "gists_url": "https://api.github.com/users/iluwatar/gists{/gist_id}",
      "starred_url": "https://api.github.com/users/iluwatar/starred{/owner}{/repo}",
      "subscriptions_url": "https://api.github.com/users/iluwatar/subscriptions",
      "organizations_url": "https://api.github.com/users/iluwatar/orgs",
      "repos_url": "https://api.github.com/users/iluwatar/repos",
      "events_url": "https://api.github.com/users/iluwatar/events{/privacy}",
      "received_events_url": "https://api.github.com/users/iluwatar/received_events",
      "type": "User",
      "site_admin": false
    },
    "repo": {
      "id": 22790488,
      "name": "java-design-patterns",
      "full_name": "iluwatar/java-design-patterns",
      "owner": {
        "login": "iluwatar",
        "id": 582346,
        "avatar_url": "https://avatars1.githubusercontent.com/u/582346?v=4",
        "gravatar_id": "",
        "url": "https://api.github.com/users/iluwatar",
        "html_url": "https://github.com/iluwatar",
        "followers_url": "https://api.github.com/users/iluwatar/followers",
        "following_url": "https://api.github.com/users/iluwatar/following{/other_user}",
        "gists_url": "https://api.github.com/users/iluwatar/gists{/gist_id}",
        "starred_url": "https://api.github.com/users/iluwatar/starred{/owner}{/repo}",
        "subscriptions_url": "https://api.github.com/users/iluwatar/subscriptions",
        "organizations_url": "https://api.github.com/users/iluwatar/orgs",
        "repos_url": "https://api.github.com/users/iluwatar/repos",
        "events_url": "https://api.github.com/users/iluwatar/events{/privacy}",
        "received_events_url": "https://api.github.com/users/iluwatar/received_events",
        "type": "User",
        "site_admin": false
      },
      "private": false,
      "html_url": "https://github.com/iluwatar/java-design-patterns",
      "description": "Design patterns implemented in Java",
      "fork": false,
      "url": "https://api.github.com/repos/iluwatar/java-design-patterns",
      "forks_url": "https://api.github.com/repos/iluwatar/java-design-patterns/forks",
      "keys_url": "https://api.github.com/repos/iluwatar/java-design-patterns/keys{/key_id}",
      "collaborators_url": "https://api.github.com/repos/iluwatar/java-design-patterns/collaborators{/collaborator}",
      "teams_url": "https://api.github.com/repos/iluwatar/java-design-patterns/teams",
      "hooks_url": "https://api.github.com/repos/iluwatar/java-design-patterns/hooks",
      "issue_events_url": "https://api.github.com/repos/iluwatar/java-design-patterns/issues/events{/number}",
      "events_url": "https://api.github.com/repos/iluwatar/java-design-patterns/events",
      "assignees_url": "https://api.github.com/repos/iluwatar/java-design-patterns/assignees{/user}",
      "branches_url": "https://api.github.com/repos/iluwatar/java-design-patterns/branches{/branch}",
      "tags_url": "https://api.github.com/repos/iluwatar/java-design-patterns/tags",
      "blobs_url": "https://api.github.com/repos/iluwatar/java-design-patterns/git/blobs{/sha}",
      "git_tags_url": "https://api.github.com/repos/iluwatar/java-design-patterns/git/tags{/sha}",
      "git_refs_url": "https://api.github.com/repos/iluwatar/java-design-patterns/git/refs{/sha}",
      "trees_url": "https://api.github.com/repos/iluwatar/java-design-patterns/git/trees{/sha}",
      "statuses_url": "https://api.github.com/repos/iluwatar/java-design-patterns/statuses/{sha}",
      "languages_url": "https://api.github.com/repos/iluwatar/java-design-patterns/languages",
      "stargazers_url": "https://api.github.com/repos/iluwatar/java-design-patterns/stargazers",
      "contributors_url": "https://api.github.com/repos/iluwatar/java-design-patterns/contributors",
      "subscribers_url": "https://api.github.com/repos/iluwatar/java-design-patterns/subscribers",
      "subscription_url": "https://api.github.com/repos/iluwatar/java-design-patterns/subscription",
      "commits_url": "https://api.github.com/repos/iluwatar/java-design-patterns/commits{/sha}",
      "git_commits_url": "https://api.github.com/repos/iluwatar/java-design-patterns/git/commits{/sha}",
      "comments_url": "https://api.github.com/repos/iluwatar/java-design-patterns/comments{/number}",
      "issue_comment_url": "https://api.github.com/repos/iluwatar/java-design-patterns/issues/comments{/number}",
      "contents_url": "https://api.github.com/repos/iluwatar/java-design-patterns/contents/{+path}",
      "compare_url": "https://api.github.com/repos/iluwatar/java-design-patterns/compare/{base}...{head}",
      "merges_url": "https://api.github.com/repos/iluwatar/java-design-patterns/merges",
      "archive_url": "https://api.github.com/repos/iluwatar/java-design-patterns/{archive_format}{/ref}",
      "downloads_url": "https://api.github.com/repos/iluwatar/java-design-patterns/downloads",
      "issues_url": "https://api.github.com/repos/iluwatar/java-design-patterns/issues{/number}",
      "pulls_url": "https://api.github.com/repos/iluwatar/java-design-patterns/pulls{/number}",
      "milestones_url": "https://api.github.com/repos/iluwatar/java-design-patterns/milestones{/number}",
      "notifications_url": "https://api.github.com/repos/iluwatar/java-design-patterns/notifications{?since,all,participating}",
      "labels_url": "https://api.github.com/repos/iluwatar/java-design-patterns/labels{/name}",
      "releases_url": "https://api.github.com/repos/iluwatar/java-design-patterns/releases{/id}",
      "deployments_url": "https://api.github.com/repos/iluwatar/java-design-patterns/deployments",
      "created_at": "2014-08-09T16:45:18Z",
      "updated_at": "2017-11-06T14:20:28Z",
      "pushed_at": "2017-11-05T13:54:18Z",
      "git_url": "git://github.com/iluwatar/java-design-patterns.git",
      "ssh_url": "git@github.com:iluwatar/java-design-patterns.git",
      "clone_url": "https://github.com/iluwatar/java-design-patterns.git",
      "svn_url": "https://github.com/iluwatar/java-design-patterns",
      "homepage": "http://java-design-patterns.com",
      "size": 16289,
      "stargazers_count": 26135,
      "watchers_count": 26135,
      "language": "Java",
      "has_issues": true,
      "has_projects": true,
      "has_downloads": true,
      "has_wiki": true,
      "has_pages": true,
      "forks_count": 8347,
      "mirror_url": null,
      "archived": false,
      "open_issues_count": 176,
      "forks": 8347,
      "open_issues": 176,
      "watchers": 26135,
      "default_branch": "master"
    }
  },
  "_links": {
    "self": {
      "href": "https://api.github.com/repos/iluwatar/java-design-patterns/pulls/663"
    },
    "html": {
      "href": "https://github.com/iluwatar/java-design-patterns/pull/663"
    },
    "issue": {
      "href": "https://api.github.com/repos/iluwatar/java-design-patterns/issues/663"
    },
    "comments": {
      "href": "https://api.github.com/repos/iluwatar/java-design-patterns/issues/663/comments"
    },
    "review_comments": {
      "href": "https://api.github.com/repos/iluwatar/java-design-patterns/pulls/663/comments"
    },
    "review_comment": {
      "href": "https://api.github.com/repos/iluwatar/java-design-patterns/pulls/comments{/number}"
    },
    "commits": {
      "href": "https://api.github.com/repos/iluwatar/java-design-patterns/pulls/663/commits"
    },
    "statuses": {
      "href": "https://api.github.com/repos/iluwatar/java-design-patterns/statuses/6e0bf59e5a7e2a768f0ddc923178e8153ba3c0ce"
    }
  },
  "author_association": "NONE"
},
{
  "url": "https://api.github.com/repos/iluwatar/java-design-patterns/pulls/660",
  "id": 149604286,
  "html_url": "https://github.com/iluwatar/java-design-patterns/pull/660",
  "diff_url": "https://github.com/iluwatar/java-design-patterns/pull/660.diff",
  "patch_url": "https://github.com/iluwatar/java-design-patterns/pull/660.patch",
  "issue_url": "https://api.github.com/repos/iluwatar/java-design-patterns/issues/660",
  "number": 660,
  "state": "open",
  "locked": false,
  "title": "updated the introduction section of this project.",
  "user": {
    "login": "Arpitjain250",
    "id": 30417007,
    "avatar_url": "https://avatars0.githubusercontent.com/u/30417007?v=4",
    "gravatar_id": "",
    "url": "https://api.github.com/users/Arpitjain250",
    "html_url": "https://github.com/Arpitjain250",
    "followers_url": "https://api.github.com/users/Arpitjain250/followers",
    "following_url": "https://api.github.com/users/Arpitjain250/following{/other_user}",
    "gists_url": "https://api.github.com/users/Arpitjain250/gists{/gist_id}",
    "starred_url": "https://api.github.com/users/Arpitjain250/starred{/owner}{/repo}",
    "subscriptions_url": "https://api.github.com/users/Arpitjain250/subscriptions",
    "organizations_url": "https://api.github.com/users/Arpitjain250/orgs",
    "repos_url": "https://api.github.com/users/Arpitjain250/repos",
    "events_url": "https://api.github.com/users/Arpitjain250/events{/privacy}",
    "received_events_url": "https://api.github.com/users/Arpitjain250/received_events",
    "type": "User",
    "site_admin": false
  },
  "body": "I think good introduction gives the programmer the correct knowledge and idea about the project.",
  "created_at": "2017-10-30T18:38:50Z",
  "updated_at": "2017-11-05T07:58:36Z",
  "closed_at": null,
  "merged_at": null,
  "merge_commit_sha": "585287563c61227076b2157c1ab9611ed70eb4b0",
  "assignee": null,
  "assignees": [

  ],
  "requested_reviewers": [

  ],
  "milestone": null,
  "commits_url": "https://api.github.com/repos/iluwatar/java-design-patterns/pulls/660/commits",
  "review_comments_url": "https://api.github.com/repos/iluwatar/java-design-patterns/pulls/660/comments",
  "review_comment_url": "https://api.github.com/repos/iluwatar/java-design-patterns/pulls/comments{/number}",
  "comments_url": "https://api.github.com/repos/iluwatar/java-design-patterns/issues/660/comments",
  "statuses_url": "https://api.github.com/repos/iluwatar/java-design-patterns/statuses/f558e1810f9fda80f91affac6892981fc2930caf",
  "head": {
    "label": "Arpitjain250:patch-1",
    "ref": "patch-1",
    "sha": "f558e1810f9fda80f91affac6892981fc2930caf",
    "user": {
      "login": "Arpitjain250",
      "id": 30417007,
      "avatar_url": "https://avatars0.githubusercontent.com/u/30417007?v=4",
      "gravatar_id": "",
      "url": "https://api.github.com/users/Arpitjain250",
      "html_url": "https://github.com/Arpitjain250",
      "followers_url": "https://api.github.com/users/Arpitjain250/followers",
      "following_url": "https://api.github.com/users/Arpitjain250/following{/other_user}",
      "gists_url": "https://api.github.com/users/Arpitjain250/gists{/gist_id}",
      "starred_url": "https://api.github.com/users/Arpitjain250/starred{/owner}{/repo}",
      "subscriptions_url": "https://api.github.com/users/Arpitjain250/subscriptions",
      "organizations_url": "https://api.github.com/users/Arpitjain250/orgs",
      "repos_url": "https://api.github.com/users/Arpitjain250/repos",
      "events_url": "https://api.github.com/users/Arpitjain250/events{/privacy}",
      "received_events_url": "https://api.github.com/users/Arpitjain250/received_events",
      "type": "User",
      "site_admin": false
    },
    "repo": {
      "id": 108892175,
      "name": "java-design-patterns",
      "full_name": "Arpitjain250/java-design-patterns",
      "owner": {
        "login": "Arpitjain250",
        "id": 30417007,
        "avatar_url": "https://avatars0.githubusercontent.com/u/30417007?v=4",
        "gravatar_id": "",
        "url": "https://api.github.com/users/Arpitjain250",
        "html_url": "https://github.com/Arpitjain250",
        "followers_url": "https://api.github.com/users/Arpitjain250/followers",
        "following_url": "https://api.github.com/users/Arpitjain250/following{/other_user}",
        "gists_url": "https://api.github.com/users/Arpitjain250/gists{/gist_id}",
        "starred_url": "https://api.github.com/users/Arpitjain250/starred{/owner}{/repo}",
        "subscriptions_url": "https://api.github.com/users/Arpitjain250/subscriptions",
        "organizations_url": "https://api.github.com/users/Arpitjain250/orgs",
        "repos_url": "https://api.github.com/users/Arpitjain250/repos",
        "events_url": "https://api.github.com/users/Arpitjain250/events{/privacy}",
        "received_events_url": "https://api.github.com/users/Arpitjain250/received_events",
        "type": "User",
        "site_admin": false
      },
      "private": false,
      "html_url": "https://github.com/Arpitjain250/java-design-patterns",
      "description": "Design patterns implemented in Java",
      "fork": true,
      "url": "https://api.github.com/repos/Arpitjain250/java-design-patterns",
      "forks_url": "https://api.github.com/repos/Arpitjain250/java-design-patterns/forks",
      "keys_url": "https://api.github.com/repos/Arpitjain250/java-design-patterns/keys{/key_id}",
      "collaborators_url": "https://api.github.com/repos/Arpitjain250/java-design-patterns/collaborators{/collaborator}",
      "teams_url": "https://api.github.com/repos/Arpitjain250/java-design-patterns/teams",
      "hooks_url": "https://api.github.com/repos/Arpitjain250/java-design-patterns/hooks",
      "issue_events_url": "https://api.github.com/repos/Arpitjain250/java-design-patterns/issues/events{/number}",
      "events_url": "https://api.github.com/repos/Arpitjain250/java-design-patterns/events",
      "assignees_url": "https://api.github.com/repos/Arpitjain250/java-design-patterns/assignees{/user}",
      "branches_url": "https://api.github.com/repos/Arpitjain250/java-design-patterns/branches{/branch}",
      "tags_url": "https://api.github.com/repos/Arpitjain250/java-design-patterns/tags",
      "blobs_url": "https://api.github.com/repos/Arpitjain250/java-design-patterns/git/blobs{/sha}",
      "git_tags_url": "https://api.github.com/repos/Arpitjain250/java-design-patterns/git/tags{/sha}",
      "git_refs_url": "https://api.github.com/repos/Arpitjain250/java-design-patterns/git/refs{/sha}",
      "trees_url": "https://api.github.com/repos/Arpitjain250/java-design-patterns/git/trees{/sha}",
      "statuses_url": "https://api.github.com/repos/Arpitjain250/java-design-patterns/statuses/{sha}",
      "languages_url": "https://api.github.com/repos/Arpitjain250/java-design-patterns/languages",
      "stargazers_url": "https://api.github.com/repos/Arpitjain250/java-design-patterns/stargazers",
      "contributors_url": "https://api.github.com/repos/Arpitjain250/java-design-patterns/contributors",
      "subscribers_url": "https://api.github.com/repos/Arpitjain250/java-design-patterns/subscribers",
      "subscription_url": "https://api.github.com/repos/Arpitjain250/java-design-patterns/subscription",
      "commits_url": "https://api.github.com/repos/Arpitjain250/java-design-patterns/commits{/sha}",
      "git_commits_url": "https://api.github.com/repos/Arpitjain250/java-design-patterns/git/commits{/sha}",
      "comments_url": "https://api.github.com/repos/Arpitjain250/java-design-patterns/comments{/number}",
      "issue_comment_url": "https://api.github.com/repos/Arpitjain250/java-design-patterns/issues/comments{/number}",
      "contents_url": "https://api.github.com/repos/Arpitjain250/java-design-patterns/contents/{+path}",
      "compare_url": "https://api.github.com/repos/Arpitjain250/java-design-patterns/compare/{base}...{head}",
      "merges_url": "https://api.github.com/repos/Arpitjain250/java-design-patterns/merges",
      "archive_url": "https://api.github.com/repos/Arpitjain250/java-design-patterns/{archive_format}{/ref}",
      "downloads_url": "https://api.github.com/repos/Arpitjain250/java-design-patterns/downloads",
      "issues_url": "https://api.github.com/repos/Arpitjain250/java-design-patterns/issues{/number}",
      "pulls_url": "https://api.github.com/repos/Arpitjain250/java-design-patterns/pulls{/number}",
      "milestones_url": "https://api.github.com/repos/Arpitjain250/java-design-patterns/milestones{/number}",
      "notifications_url": "https://api.github.com/repos/Arpitjain250/java-design-patterns/notifications{?since,all,participating}",
      "labels_url": "https://api.github.com/repos/Arpitjain250/java-design-patterns/labels{/name}",
      "releases_url": "https://api.github.com/repos/Arpitjain250/java-design-patterns/releases{/id}",
      "deployments_url": "https://api.github.com/repos/Arpitjain250/java-design-patterns/deployments",
      "created_at": "2017-10-30T18:32:56Z",
      "updated_at": "2017-10-30T18:33:01Z",
      "pushed_at": "2017-10-30T18:37:25Z",
      "git_url": "git://github.com/Arpitjain250/java-design-patterns.git",
      "ssh_url": "git@github.com:Arpitjain250/java-design-patterns.git",
      "clone_url": "https://github.com/Arpitjain250/java-design-patterns.git",
      "svn_url": "https://github.com/Arpitjain250/java-design-patterns",
      "homepage": "http://java-design-patterns.com",
      "size": 16298,
      "stargazers_count": 0,
      "watchers_count": 0,
      "language": "Java",
      "has_issues": false,
      "has_projects": true,
      "has_downloads": true,
      "has_wiki": true,
      "has_pages": false,
      "forks_count": 0,
      "mirror_url": null,
      "archived": false,
      "open_issues_count": 0,
      "forks": 0,
      "open_issues": 0,
      "watchers": 0,
      "default_branch": "master"
    }
  },
  "base": {
    "label": "iluwatar:master",
    "ref": "master",
    "sha": "5ed46c2c6481c322673c6eacab918302ca1d5f13",
    "user": {
      "login": "iluwatar",
      "id": 582346,
      "avatar_url": "https://avatars1.githubusercontent.com/u/582346?v=4",
      "gravatar_id": "",
      "url": "https://api.github.com/users/iluwatar",
      "html_url": "https://github.com/iluwatar",
      "followers_url": "https://api.github.com/users/iluwatar/followers",
      "following_url": "https://api.github.com/users/iluwatar/following{/other_user}",
      "gists_url": "https://api.github.com/users/iluwatar/gists{/gist_id}",
      "starred_url": "https://api.github.com/users/iluwatar/starred{/owner}{/repo}",
      "subscriptions_url": "https://api.github.com/users/iluwatar/subscriptions",
      "organizations_url": "https://api.github.com/users/iluwatar/orgs",
      "repos_url": "https://api.github.com/users/iluwatar/repos",
      "events_url": "https://api.github.com/users/iluwatar/events{/privacy}",
      "received_events_url": "https://api.github.com/users/iluwatar/received_events",
      "type": "User",
      "site_admin": false
    },
    "repo": {
      "id": 22790488,
      "name": "java-design-patterns",
      "full_name": "iluwatar/java-design-patterns",
      "owner": {
        "login": "iluwatar",
        "id": 582346,
        "avatar_url": "https://avatars1.githubusercontent.com/u/582346?v=4",
        "gravatar_id": "",
        "url": "https://api.github.com/users/iluwatar",
        "html_url": "https://github.com/iluwatar",
        "followers_url": "https://api.github.com/users/iluwatar/followers",
        "following_url": "https://api.github.com/users/iluwatar/following{/other_user}",
        "gists_url": "https://api.github.com/users/iluwatar/gists{/gist_id}",
        "starred_url": "https://api.github.com/users/iluwatar/starred{/owner}{/repo}",
        "subscriptions_url": "https://api.github.com/users/iluwatar/subscriptions",
        "organizations_url": "https://api.github.com/users/iluwatar/orgs",
        "repos_url": "https://api.github.com/users/iluwatar/repos",
        "events_url": "https://api.github.com/users/iluwatar/events{/privacy}",
        "received_events_url": "https://api.github.com/users/iluwatar/received_events",
        "type": "User",
        "site_admin": false
      },
      "private": false,
      "html_url": "https://github.com/iluwatar/java-design-patterns",
      "description": "Design patterns implemented in Java",
      "fork": false,
      "url": "https://api.github.com/repos/iluwatar/java-design-patterns",
      "forks_url": "https://api.github.com/repos/iluwatar/java-design-patterns/forks",
      "keys_url": "https://api.github.com/repos/iluwatar/java-design-patterns/keys{/key_id}",
      "collaborators_url": "https://api.github.com/repos/iluwatar/java-design-patterns/collaborators{/collaborator}",
      "teams_url": "https://api.github.com/repos/iluwatar/java-design-patterns/teams",
      "hooks_url": "https://api.github.com/repos/iluwatar/java-design-patterns/hooks",
      "issue_events_url": "https://api.github.com/repos/iluwatar/java-design-patterns/issues/events{/number}",
      "events_url": "https://api.github.com/repos/iluwatar/java-design-patterns/events",
      "assignees_url": "https://api.github.com/repos/iluwatar/java-design-patterns/assignees{/user}",
      "branches_url": "https://api.github.com/repos/iluwatar/java-design-patterns/branches{/branch}",
      "tags_url": "https://api.github.com/repos/iluwatar/java-design-patterns/tags",
      "blobs_url": "https://api.github.com/repos/iluwatar/java-design-patterns/git/blobs{/sha}",
      "git_tags_url": "https://api.github.com/repos/iluwatar/java-design-patterns/git/tags{/sha}",
      "git_refs_url": "https://api.github.com/repos/iluwatar/java-design-patterns/git/refs{/sha}",
      "trees_url": "https://api.github.com/repos/iluwatar/java-design-patterns/git/trees{/sha}",
      "statuses_url": "https://api.github.com/repos/iluwatar/java-design-patterns/statuses/{sha}",
      "languages_url": "https://api.github.com/repos/iluwatar/java-design-patterns/languages",
      "stargazers_url": "https://api.github.com/repos/iluwatar/java-design-patterns/stargazers",
      "contributors_url": "https://api.github.com/repos/iluwatar/java-design-patterns/contributors",
      "subscribers_url": "https://api.github.com/repos/iluwatar/java-design-patterns/subscribers",
      "subscription_url": "https://api.github.com/repos/iluwatar/java-design-patterns/subscription",
      "commits_url": "https://api.github.com/repos/iluwatar/java-design-patterns/commits{/sha}",
      "git_commits_url": "https://api.github.com/repos/iluwatar/java-design-patterns/git/commits{/sha}",
      "comments_url": "https://api.github.com/repos/iluwatar/java-design-patterns/comments{/number}",
      "issue_comment_url": "https://api.github.com/repos/iluwatar/java-design-patterns/issues/comments{/number}",
      "contents_url": "https://api.github.com/repos/iluwatar/java-design-patterns/contents/{+path}",
      "compare_url": "https://api.github.com/repos/iluwatar/java-design-patterns/compare/{base}...{head}",
      "merges_url": "https://api.github.com/repos/iluwatar/java-design-patterns/merges",
      "archive_url": "https://api.github.com/repos/iluwatar/java-design-patterns/{archive_format}{/ref}",
      "downloads_url": "https://api.github.com/repos/iluwatar/java-design-patterns/downloads",
      "issues_url": "https://api.github.com/repos/iluwatar/java-design-patterns/issues{/number}",
      "pulls_url": "https://api.github.com/repos/iluwatar/java-design-patterns/pulls{/number}",
      "milestones_url": "https://api.github.com/repos/iluwatar/java-design-patterns/milestones{/number}",
      "notifications_url": "https://api.github.com/repos/iluwatar/java-design-patterns/notifications{?since,all,participating}",
      "labels_url": "https://api.github.com/repos/iluwatar/java-design-patterns/labels{/name}",
      "releases_url": "https://api.github.com/repos/iluwatar/java-design-patterns/releases{/id}",
      "deployments_url": "https://api.github.com/repos/iluwatar/java-design-patterns/deployments",
      "created_at": "2014-08-09T16:45:18Z",
      "updated_at": "2017-11-06T14:20:28Z",
      "pushed_at": "2017-11-05T13:54:18Z",
      "git_url": "git://github.com/iluwatar/java-design-patterns.git",
      "ssh_url": "git@github.com:iluwatar/java-design-patterns.git",
      "clone_url": "https://github.com/iluwatar/java-design-patterns.git",
      "svn_url": "https://github.com/iluwatar/java-design-patterns",
      "homepage": "http://java-design-patterns.com",
      "size": 16289,
      "stargazers_count": 26135,
      "watchers_count": 26135,
      "language": "Java",
      "has_issues": true,
      "has_projects": true,
      "has_downloads": true,
      "has_wiki": true,
      "has_pages": true,
      "forks_count": 8347,
      "mirror_url": null,
      "archived": false,
      "open_issues_count": 176,
      "forks": 8347,
      "open_issues": 176,
      "watchers": 26135,
      "default_branch": "master"
    }
  },
  "_links": {
    "self": {
      "href": "https://api.github.com/repos/iluwatar/java-design-patterns/pulls/660"
    },
    "html": {
      "href": "https://github.com/iluwatar/java-design-patterns/pull/660"
    },
    "issue": {
      "href": "https://api.github.com/repos/iluwatar/java-design-patterns/issues/660"
    },
    "comments": {
      "href": "https://api.github.com/repos/iluwatar/java-design-patterns/issues/660/comments"
    },
    "review_comments": {
      "href": "https://api.github.com/repos/iluwatar/java-design-patterns/pulls/660/comments"
    },
    "review_comment": {
      "href": "https://api.github.com/repos/iluwatar/java-design-patterns/pulls/comments{/number}"
    },
    "commits": {
      "href": "https://api.github.com/repos/iluwatar/java-design-patterns/pulls/660/commits"
    },
    "statuses": {
      "href": "https://api.github.com/repos/iluwatar/java-design-patterns/statuses/f558e1810f9fda80f91affac6892981fc2930caf"
    }
  },
  "author_association": "NONE"
}
]